django_gem_taxonomy/__init__.py
django_gem_taxonomy/apps.py
django_gem_taxonomy/models.py
django_gem_taxonomy/urls.py
django_gem_taxonomy/urls_api_v1.py
django_gem_taxonomy/version.py
django_gem_taxonomy/views.py
django_gem_taxonomy/management/__init__.py
django_gem_taxonomy/management/commands/__init__.py
django_gem_taxonomy/management/commands/taxonomy_load_standard.py
django_gem_taxonomy/migrations/0001_initial.py
django_gem_taxonomy/migrations/__init__.py
django_gem_taxonomy/static/taxonomy/css/taxonomy_help.css
django_gem_taxonomy/static/taxonomy_v3/css/dist/bootstrap.min.css
django_gem_taxonomy/static/taxonomy_v3/js/homepage.js
django_gem_taxonomy/static/taxonomy_v3/js/dist/bootstrap.bundle.min.js
django_gem_taxonomy/static/taxonomy_v3/js/dist/jquery.min.js
django_gem_taxonomy/static/taxonomy_v3/json/taxonomy_standard4taxtweb.json
django_gem_taxonomy/templates/django-gem-taxonomy/homepage/homepage.html
django_gem_taxonomy/templates/django-gem-taxonomy/structure/atom.html
django_gem_taxonomy/templates/django-gem-taxonomy/structure/atoms_group.html
django_gem_taxonomy/templates/django-gem-taxonomy/structure/attribute.html
django_gem_taxonomy/templates/django-gem-taxonomy/structure/param.html
django_gem_taxonomy/templates/django-gem-taxonomy/taxcomm/taxcomm_incl.js
django_gem_taxonomy/templates/django-gem-taxonomy/taxgraph/taxgraph.html
django_gem_taxonomy/templates/django-gem-taxonomy/taxgraph/taxgraph_incl.js
django_gem_taxonomy-1.4.3.dist-info/licenses/LICENSE
django_gem_taxonomy-1.4.3.dist-info/METADATA
django_gem_taxonomy-1.4.3.dist-info/WHEEL
django_gem_taxonomy-1.4.3.dist-info/top_level.txt
django_gem_taxonomy-1.4.3.dist-info/RECORD
