Metadata-Version: 2.4
Name: django-gem-taxonomy
Version: 1.4.3
Summary: Django Gem Taxonomy - apps and web services that are part of the GEM Taxonomy suite
Author-email: Matteo Nastasi <nastasi@openquake.org>
License:                     GNU AFFERO GENERAL PUBLIC LICENSE
Keywords: GEM,taxonomy,standard,openquake,webservice,taxtgraph
Classifier: License :: OSI Approved :: Apache Software License
License-File: LICENSE
Requires-Dist: django~=4.2
Requires-Dist: djangorestframework~=3.15
Requires-Dist: openquake.gem-taxonomy~=1.11
Provides-Extra: test
Requires-Dist: pytest; extra == "test"
Requires-Dist: pytest-django; extra == "test"
Dynamic: license-file
